yt_dlp_plugins/extractor/invidious.py
yt_dlp_plugins/extractor/youtube_override.py
yt_dlp_invidious-0.1.1.dist-info/METADATA
yt_dlp_invidious-0.1.1.dist-info/WHEEL
yt_dlp_invidious-0.1.1.dist-info/licenses/LICENSE
yt_dlp_invidious-0.1.1.dist-info/RECORD
