Metadata-Version: 2.3
Name: yt-dlp-invidious
Version: 0.1.1
Author: grqz
License: This is free and unencumbered software released into the public domain.
License-File: LICENSE
Keywords: yt-dlp,yt-dlp-plugin
Requires-Python: >=3.8
